KnotLinkClient_Py/OpenSocketQuerier.py
KnotLinkClient_Py/OpenSocketResponser.py
KnotLinkClient_Py/SignalSender.py
KnotLinkClient_Py/SignalSubscriber.py
KnotLinkClient_Py/__init__.py
KnotLinkClient_Py/kludf.py
KnotLinkClient_Py/tcpclient.py
knotlinkclient_py-1.0.4.dist-info/METADATA
knotlinkclient_py-1.0.4.dist-info/WHEEL
knotlinkclient_py-1.0.4.dist-info/top_level.txt
knotlinkclient_py-1.0.4.dist-info/RECORD
