Metadata-Version: 2.1
Name: KnotLinkClient_Py
Version: 1.0.4
Summary: A Py-based client for KnotLink communication
Author: HXH
Author-email: 1768224274@qq.com
Classifier: Programming Language :: Python :: 3
Classifier: Operating System :: OS Independent
Classifier: Topic :: Software Development :: Libraries :: Python Modules
Classifier: Intended Audience :: Developers
